helius_sdk/__init__.py
helius_sdk/__main__.py
helius_sdk/cli.py
helius_sdk/core.py
helius_sdk/event.py
helius_sdk/nft.py
helius_sdk/transaction.py
helius_sdk/conf/base.yml
helius_sdk-0.0.11.dist-info/AUTHORS.rst
helius_sdk-0.0.11.dist-info/LICENSE
helius_sdk-0.0.11.dist-info/METADATA
helius_sdk-0.0.11.dist-info/WHEEL
helius_sdk-0.0.11.dist-info/entry_points.txt
helius_sdk-0.0.11.dist-info/top_level.txt
helius_sdk-0.0.11.dist-info/RECORD
