Metadata-Version: 1.2
Name: helius-sdk
Version: 0.0.11
Summary: Helius SDK
Home-page: https://github.com/mmchougule/helius-sdk-python
Author: Mayur Chougule
Author-email: mayurchougule1@gmail.com
License: MIT
Project-URL: Documentation, https://helius-sdk-python.readthedocs.io/
Project-URL: Changelog, https://helius-sdk-python.readthedocs.io/en/latest/changelog.html
Project-URL: Issue Tracker, https://github.com/mmchougule/helius-sdk-python/issues
Platform: UNKNOWN
Classifier: Development Status :: 5 - Production/Stable
Classifier: Intended Audience :: Developers
Classifier: License :: OSI Approved :: MIT License
Classifier: Operating System :: Unix
Classifier: Operating System :: POSIX
Classifier: Operating System :: Microsoft :: Windows
Classifier: Programming Language :: Python
Classifier: Programming Language :: Python :: 3.8
Classifier: Programming Language :: Python :: 3.9
Classifier: Programming Language :: Python :: 3.10
Classifier: Programming Language :: Python :: 3.11
Classifier: Programming Language :: Python :: Implementation :: CPython
Classifier: Programming Language :: Python :: Implementation :: PyPy
Classifier: Topic :: Utilities
Requires-Python: >=3.7
